utaupy/__init__.py
utaupy/backup.py
utaupy/convert.py
utaupy/hts.py
utaupy/label.py
utaupy/otoini.py
utaupy/reaper.py
utaupy/reclist.py
utaupy/setparam.py
utaupy/shiro.py
utaupy/svp.py
utaupy/table.py
utaupy/ust.py
utaupy/utau.py
utaupy/utauplugin.py
utaupy/utils/__init__.py
utaupy/utils/_hts2csv.py
utaupy/utils/_hts2json.py
utaupy/utils/_hts2ust.py
utaupy/utils/_ust2hts.py
utaupy-1.22.1.dist-info/licenses/LICENSE.md
utaupy-1.22.1.dist-info/METADATA
utaupy-1.22.1.dist-info/WHEEL
utaupy-1.22.1.dist-info/top_level.txt
utaupy-1.22.1.dist-info/RECORD
