Metadata-Version: 2.4
Name: utaupy
Version: 1.22.1
Summary: Python3 module for UTAU and singing-databases
Author-email: oatsu <oatsu.dev@gmail.com>
Maintainer-email: oatsu <oatsu.dev@gmail.com>
Project-URL: Homepage, https://github.com/oatsu-gh/utaupy
Keywords: UTAU
Classifier: Programming Language :: Python :: 3
Requires-Python: >=3.9
License-File: LICENSE.md
Dynamic: license-file
